azure/mgmt/dynatrace/__init__.py
azure/mgmt/dynatrace/_configuration.py
azure/mgmt/dynatrace/_dynatrace_observability_mgmt_client.py
azure/mgmt/dynatrace/_patch.py
azure/mgmt/dynatrace/_serialization.py
azure/mgmt/dynatrace/_vendor.py
azure/mgmt/dynatrace/_version.py
azure/mgmt/dynatrace/py.typed
azure/mgmt/dynatrace/aio/__init__.py
azure/mgmt/dynatrace/aio/_configuration.py
azure/mgmt/dynatrace/aio/_dynatrace_observability_mgmt_client.py
azure/mgmt/dynatrace/aio/_patch.py
azure/mgmt/dynatrace/aio/operations/__init__.py
azure/mgmt/dynatrace/aio/operations/_monitors_operations.py
azure/mgmt/dynatrace/aio/operations/_operations.py
azure/mgmt/dynatrace/aio/operations/_patch.py
azure/mgmt/dynatrace/aio/operations/_single_sign_on_operations.py
azure/mgmt/dynatrace/aio/operations/_tag_rules_operations.py
azure/mgmt/dynatrace/models/__init__.py
azure/mgmt/dynatrace/models/_dynatrace_observability_mgmt_client_enums.py
azure/mgmt/dynatrace/models/_models_py3.py
azure/mgmt/dynatrace/models/_patch.py
azure/mgmt/dynatrace/operations/__init__.py
azure/mgmt/dynatrace/operations/_monitors_operations.py
azure/mgmt/dynatrace/operations/_operations.py
azure/mgmt/dynatrace/operations/_patch.py
azure/mgmt/dynatrace/operations/_single_sign_on_operations.py
azure/mgmt/dynatrace/operations/_tag_rules_operations.py
azure_mgmt_dynatrace-2.0.0.dist-info/LICENSE
azure_mgmt_dynatrace-2.0.0.dist-info/METADATA
azure_mgmt_dynatrace-2.0.0.dist-info/WHEEL
azure_mgmt_dynatrace-2.0.0.dist-info/top_level.txt
azure_mgmt_dynatrace-2.0.0.dist-info/RECORD
